owid/datautils/__init__.py
owid/datautils/checks.py
owid/datautils/common.py
owid/datautils/dataframes.py
owid/datautils/decorators.py
owid/datautils/ui.py
owid/datautils/web.py
owid/datautils/format/__init__.py
owid/datautils/format/numbers.py
owid/datautils/google/__init__.py
owid/datautils/google/api.py
owid/datautils/google/config.py
owid/datautils/google/sheets.py
owid/datautils/io/__init__.py
owid/datautils/io/archive.py
owid/datautils/io/df.py
owid/datautils/io/json.py
owid_datautils-0.6.1.dist-info/METADATA
owid_datautils-0.6.1.dist-info/WHEEL
owid_datautils-0.6.1.dist-info/licenses/LICENSE
owid_datautils-0.6.1.dist-info/RECORD
